{
  "themes": [
    {
      "id": "ddr5_memory",
      "name": "DDR5",
      "keyword": "DDR5",
      "supply_chain": {
        "upstream": [],
        "downstream": []
      },
      "tw_stocks": [
        {
          "code": "2408",
          "name": "南亞科"
        },
        {
          "code": "3260",
          "name": "威剛"
        },
        {
          "code": "1303",
          "name": "南亞"
        },
        {
          "code": "6669",
          "name": "緯穎"
        },
        {
          "code": "5289",
          "name": "宜鼎"
        }
      ],
      "us_stocks": [],
      "auto_created": true,
      "auto_created_at": "2026-05-05"
    },
    {
      "id": "consumer_electronics_manufacturing",
      "name": "消費電子代工",
      "keyword": "消費電子代工",
      "supply_chain": {
        "upstream": [],
        "downstream": []
      },
      "tw_stocks": [
        {
          "code": "2317",
          "name": "鴻海"
        },
        {
          "code": "2313",
          "name": "華通"
        },
        {
          "code": "2303",
          "name": "聯電"
        },
        {
          "code": "3481",
          "name": "群創"
        },
        {
          "code": "3211",
          "name": "順達"
        },
        {
          "code": "8069",
          "name": "元太"
        }
      ],
      "us_stocks": [
        {
          "ticker": "AAPL",
          "name": "Apple Inc."
        }
      ],
      "auto_created": true,
      "auto_created_at": "2026-05-05"
    },
    {
      "id": "cloud_networking_equipment",
      "name": "雲端網路",
      "keyword": "雲端網路",
      "supply_chain": {
        "upstream": [],
        "downstream": []
      },
      "tw_stocks": [
        {
          "code": "2317",
          "name": "鴻海"
        },
        {
          "code": "6274",
          "name": "台燿"
        },
        {
          "code": "2301",
          "name": "光寶科"
        },
        {
          "code": "2345",
          "name": "智邦"
        },
        {
          "code": "6285",
          "name": "啟碁"
        }
      ],
      "us_stocks": [
        {
          "ticker": "NOK",
          "name": "Nokia Corporation Sponsored"
        },
        {
          "ticker": "ONDS",
          "name": "Ondas Inc"
        }
      ],
      "auto_created": true,
      "auto_created_at": "2026-05-05"
    },
    {
      "id": "computer_terminals",
      "name": "電腦終端",
      "keyword": "電腦終端",
      "supply_chain": {
        "upstream": [],
        "downstream": []
      },
      "tw_stocks": [
        {
          "code": "2317",
          "name": "鴻海"
        }
      ],
      "us_stocks": [
        {
          "ticker": "AAPL",
          "name": "Apple Inc."
        }
      ],
      "auto_created": true,
      "auto_created_at": "2026-05-05"
    },
    {
      "id": "satellite_communication_pwb",
      "name": "衛星通訊",
      "keyword": "衛星通訊",
      "supply_chain": {
        "upstream": [],
        "downstream": []
      },
      "tw_stocks": [
        {
          "code": "2313",
          "name": "華通"
        },
        {
          "code": "3105",
          "name": "穩懋"
        },
        {
          "code": "8046",
          "name": "南電"
        },
        {
          "code": "2383",
          "name": "台光電"
        },
        {
          "code": "6187",
          "name": "萬潤"
        }
      ],
      "us_stocks": [
        {
          "ticker": "RKLB",
          "name": "Rocket Lab Corporation"
        },
        {
          "ticker": "RDW",
          "name": "Redwire Corporation"
        }
      ],
      "auto_created": true,
      "auto_created_at": "2026-05-05"
    },
    {
      "id": "ai_server_datacenter",
      "name": "AI伺服器/資料中心",
      "keyword": "AI伺服器",
      "supply_chain": {
        "upstream": [],
        "downstream": []
      },
      "tw_stocks": [
        {
          "code": "2313",
          "name": "華通"
        },
        {
          "code": "2337",
          "name": "旺宏"
        },
        {
          "code": "3037",
          "name": "欣興"
        },
        {
          "code": "3017",
          "name": "奇鋐"
        },
        {
          "code": "2308",
          "name": "台達電"
        },
        {
          "code": "2449",
          "name": "京元電子"
        },
        {
          "code": "3711",
          "name": "日月光投控"
        },
        {
          "code": "3105",
          "name": "穩懋"
        },
        {
          "code": "8299",
          "name": "群聯"
        },
        {
          "code": "4958",
          "name": "臻鼎-KY"
        },
        {
          "code": "6274",
          "name": "台燿"
        },
        {
          "code": "6147",
          "name": "頎邦"
        },
        {
          "code": "2303",
          "name": "聯電"
        },
        {
          "code": "2327",
          "name": "國巨*"
        },
        {
          "code": "8046",
          "name": "南電"
        },
        {
          "code": "2455",
          "name": "全新"
        },
        {
          "code": "6488",
          "name": "環球晶"
        },
        {
          "code": "6669",
          "name": "緯穎"
        },
        {
          "code": "1802",
          "name": "台玻"
        },
        {
          "code": "2383",
          "name": "台光電"
        },
        {
          "code": "3665",
          "name": "貿聯-KY"
        },
        {
          "code": "2301",
          "name": "光寶科"
        },
        {
          "code": "3189",
          "name": "景碩"
        },
        {
          "code": "2345",
          "name": "智邦"
        },
        {
          "code": "2360",
          "name": "致茂"
        },
        {
          "code": "4979",
          "name": "華星光"
        },
        {
          "code": "3661",
          "name": "世芯-KY"
        },
        {
          "code": "5289",
          "name": "宜鼎"
        },
        {
          "code": "1815",
          "name": "富喬"
        },
        {
          "code": "1785",
          "name": "光洋科"
        },
        {
          "code": "8210",
          "name": "勤誠"
        },
        {
          "code": "5274",
          "name": "信驊"
        },
        {
          "code": "8086",
          "name": "宏捷科"
        },
        {
          "code": "3264",
          "name": "欣銓"
        },
        {
          "code": "3324",
          "name": "雙鴻"
        },
        {
          "code": "4991",
          "name": "環宇-KY"
        }
      ],
      "us_stocks": [
        {
          "ticker": "MU",
          "name": "Micron Technology, Inc."
        },
        {
          "ticker": "INTC",
          "name": "Intel Corporation"
        },
        {
          "ticker": "IREN",
          "name": "IREN LIMITED"
        },
        {
          "ticker": "SMCI",
          "name": "Super Micro Computer, Inc."
        },
        {
          "ticker": "WULF",
          "name": "TeraWulf Inc."
        },
        {
          "ticker": "CRWV",
          "name": "CoreWeave, Inc."
        }
      ],
      "auto_created": true,
      "auto_created_at": "2026-05-05"
    },
    {
      "id": "hdi_pcb",
      "name": "HDI PCB",
      "keyword": "HDI PCB",
      "supply_chain": {
        "upstream": [],
        "downstream": []
      },
      "tw_stocks": [
        {
          "code": "2313",
          "name": "華通"
        },
        {
          "code": "3037",
          "name": "欣興"
        },
        {
          "code": "4958",
          "name": "臻鼎-KY"
        },
        {
          "code": "6274",
          "name": "台燿"
        }
      ],
      "us_stocks": [],
      "auto_created": true,
      "auto_created_at": "2026-05-05"
    },
    {
      "id": "asic_design_concept",
      "name": "ASIC",
      "keyword": "ASIC",
      "supply_chain": {
        "upstream": [],
        "downstream": []
      },
      "tw_stocks": [
        {
          "code": "2454",
          "name": "聯發科"
        },
        {
          "code": "3017",
          "name": "奇鋐"
        },
        {
          "code": "2449",
          "name": "京元電子"
        },
        {
          "code": "3711",
          "name": "日月光投控"
        },
        {
          "code": "3443",
          "name": "創意"
        },
        {
          "code": "8299",
          "name": "群聯"
        },
        {
          "code": "2303",
          "name": "聯電"
        },
        {
          "code": "6669",
          "name": "緯穎"
        },
        {
          "code": "2360",
          "name": "致茂"
        },
        {
          "code": "3661",
          "name": "世芯-KY"
        },
        {
          "code": "3264",
          "name": "欣銓"
        }
      ],
      "us_stocks": [],
      "auto_created": true,
      "auto_created_at": "2026-05-05"
    },
    {
      "id": "semiconductor_design_concept",
      "name": "半導體設計",
      "keyword": "半導體設計",
      "supply_chain": {
        "upstream": [],
        "downstream": []
      },
      "tw_stocks": [
        {
          "code": "2454",
          "name": "聯發科"
        },
        {
          "code": "3443",
          "name": "創意"
        },
        {
          "code": "3105",
          "name": "穩懋"
        },
        {
          "code": "8299",
          "name": "群聯"
        },
        {
          "code": "2303",
          "name": "聯電"
        },
        {
          "code": "1303",
          "name": "南亞"
        },
        {
          "code": "6488",
          "name": "環球晶"
        },
        {
          "code": "3661",
          "name": "世芯-KY"
        },
        {
          "code": "5274",
          "name": "信驊"
        },
        {
          "code": "3211",
          "name": "順達"
        },
        {
          "code": "3529",
          "name": "力旺"
        },
        {
          "code": "3008",
          "name": "大立光"
        },
        {
          "code": "4966",
          "name": "譜瑞-KY"
        }
      ],
      "us_stocks": [
        {
          "ticker": "INTC",
          "name": "Intel Corporation"
        },
        {
          "ticker": "AMD",
          "name": "Advanced Micro Devices, Inc."
        },
        {
          "ticker": "NVTS",
          "name": "Navitas Semiconductor Corporati"
        },
        {
          "ticker": "ARM",
          "name": "Arm Holdings plc"
        },
        {
          "ticker": "HIMX",
          "name": "Himax Technologies, Inc."
        },
        {
          "ticker": "QCOM",
          "name": "QUALCOMM Incorporated"
        }
      ],
      "auto_created": true,
      "auto_created_at": "2026-05-05"
    },
    {
      "id": "memory_chip_concept",
      "name": "記憶體",
      "keyword": "記憶體",
      "supply_chain": {
        "upstream": [],
        "downstream": []
      },
      "tw_stocks": [
        {
          "code": "2337",
          "name": "旺宏"
        },
        {
          "code": "8299",
          "name": "群聯"
        },
        {
          "code": "2344",
          "name": "華邦電"
        },
        {
          "code": "3260",
          "name": "威剛"
        },
        {
          "code": "1303",
          "name": "南亞"
        },
        {
          "code": "6669",
          "name": "緯穎"
        },
        {
          "code": "6770",
          "name": "力積電"
        },
        {
          "code": "5289",
          "name": "宜鼎"
        },
        {
          "code": "3529",
          "name": "力旺"
        },
        {
          "code": "3264",
          "name": "欣銓"
        }
      ],
      "us_stocks": [
        {
          "ticker": "MU",
          "name": "Micron Technology, Inc."
        }
      ],
      "auto_created": true,
      "auto_created_at": "2026-05-05"
    },
    {
      "id": "advanced_packaging_concept",
      "name": "先進封裝",
      "keyword": "先進封裝",
      "supply_chain": {
        "upstream": [],
        "downstream": []
      },
      "tw_stocks": [
        {
          "code": "3037",
          "name": "欣興"
        },
        {
          "code": "2449",
          "name": "京元電子"
        },
        {
          "code": "3711",
          "name": "日月光投控"
        },
        {
          "code": "6147",
          "name": "頎邦"
        },
        {
          "code": "2303",
          "name": "聯電"
        },
        {
          "code": "5289",
          "name": "宜鼎"
        },
        {
          "code": "4749",
          "name": "新應材"
        },
        {
          "code": "6187",
          "name": "萬潤"
        }
      ],
      "us_stocks": [],
      "auto_created": true,
      "auto_created_at": "2026-05-05"
    },
    {
      "id": "abf_substrate_concept",
      "name": "ABF載板",
      "keyword": "ABF載板",
      "supply_chain": {
        "upstream": [],
        "downstream": []
      },
      "tw_stocks": [
        {
          "code": "3037",
          "name": "欣興"
        },
        {
          "code": "4958",
          "name": "臻鼎-KY"
        },
        {
          "code": "8046",
          "name": "南電"
        },
        {
          "code": "3189",
          "name": "景碩"
        },
        {
          "code": "3661",
          "name": "世芯-KY"
        }
      ],
      "us_stocks": [],
      "auto_created": true,
      "auto_created_at": "2026-05-05"
    },
    {
      "id": "server_cooling_concept",
      "name": "伺服器散熱",
      "keyword": "伺服器散熱",
      "supply_chain": {
        "upstream": [],
        "downstream": []
      },
      "tw_stocks": [
        {
          "code": "3017",
          "name": "奇鋐"
        },
        {
          "code": "2308",
          "name": "台達電"
        },
        {
          "code": "3653",
          "name": "健策"
        },
        {
          "code": "3324",
          "name": "雙鴻"
        },
        {
          "code": "6187",
          "name": "萬潤"
        }
      ],
      "us_stocks": [],
      "auto_created": true,
      "auto_created_at": "2026-05-05"
    },
    {
      "id": "liquid_cooling_concept",
      "name": "水冷散熱",
      "keyword": "水冷散熱",
      "supply_chain": {
        "upstream": [],
        "downstream": []
      },
      "tw_stocks": [
        {
          "code": "3017",
          "name": "奇鋐"
        },
        {
          "code": "2308",
          "name": "台達電"
        },
        {
          "code": "2345",
          "name": "智邦"
        },
        {
          "code": "5289",
          "name": "宜鼎"
        },
        {
          "code": "3324",
          "name": "雙鴻"
        },
        {
          "code": "6187",
          "name": "萬潤"
        }
      ],
      "us_stocks": [],
      "auto_created": true,
      "auto_created_at": "2026-05-05"
    },
    {
      "id": "ic_testing_concept",
      "name": "IC測試",
      "keyword": "IC測試",
      "supply_chain": {
        "upstream": [],
        "downstream": []
      },
      "tw_stocks": [
        {
          "code": "2449",
          "name": "京元電子"
        },
        {
          "code": "3711",
          "name": "日月光投控"
        },
        {
          "code": "6147",
          "name": "頎邦"
        },
        {
          "code": "2360",
          "name": "致茂"
        },
        {
          "code": "6223",
          "name": "旺矽"
        },
        {
          "code": "3374",
          "name": "精材"
        },
        {
          "code": "3211",
          "name": "順達"
        },
        {
          "code": "3264",
          "name": "欣銓"
        }
      ],
      "us_stocks": [],
      "auto_created": true,
      "auto_created_at": "2026-05-05"
    },
    {
      "id": "foplp_concept",
      "name": "FOPLP",
      "keyword": "FOPLP",
      "supply_chain": {
        "upstream": [],
        "downstream": []
      },
      "tw_stocks": [
        {
          "code": "2449",
          "name": "京元電子"
        },
        {
          "code": "3711",
          "name": "日月光投控"
        },
        {
          "code": "3481",
          "name": "群創"
        },
        {
          "code": "4749",
          "name": "新應材"
        }
      ],
      "us_stocks": [],
      "auto_created": true,
      "auto_created_at": "2026-05-05"
    },
    {
      "id": "robotics_era_concept",
      "name": "機器人時代",
      "keyword": "機器人時代",
      "supply_chain": {
        "upstream": [],
        "downstream": []
      },
      "tw_stocks": [
        {
          "code": "3711",
          "name": "日月光投控"
        },
        {
          "code": "6187",
          "name": "萬潤"
        }
      ],
      "us_stocks": [
        {
          "ticker": "ONDS",
          "name": "Ondas Inc"
        }
      ],
      "auto_created": true,
      "auto_created_at": "2026-05-05"
    },
    {
      "id": "silicon_photonics_concept",
      "name": "矽光子",
      "keyword": "矽光子",
      "supply_chain": {
        "upstream": [],
        "downstream": []
      },
      "tw_stocks": [
        {
          "code": "3711",
          "name": "日月光投控"
        },
        {
          "code": "3443",
          "name": "創意"
        },
        {
          "code": "6147",
          "name": "頎邦"
        },
        {
          "code": "8046",
          "name": "南電"
        },
        {
          "code": "2455",
          "name": "全新"
        },
        {
          "code": "2360",
          "name": "致茂"
        },
        {
          "code": "3081",
          "name": "聯亞"
        }
      ],
      "us_stocks": [
        {
          "ticker": "GLW",
          "name": "Corning Incorporated"
        },
        {
          "ticker": "HIMX",
          "name": "Himax Technologies, Inc."
        }
      ],
      "auto_created": true,
      "auto_created_at": "2026-05-05"
    },
    {
      "id": "cpu_design_concept",
      "name": "CPU設計",
      "keyword": "CPU設計",
      "supply_chain": {
        "upstream": [],
        "downstream": []
      },
      "tw_stocks": [
        {
          "code": "3443",
          "name": "創意"
        }
      ],
      "us_stocks": [
        {
          "ticker": "INTC",
          "name": "Intel Corporation"
        },
        {
          "ticker": "AMD",
          "name": "Advanced Micro Devices, Inc."
        },
        {
          "ticker": "ARM",
          "name": "Arm Holdings plc"
        }
      ],
      "auto_created": true,
      "auto_created_at": "2026-05-05"
    },
    {
      "id": "adas_concept",
      "name": "ADAS",
      "keyword": "ADAS",
      "supply_chain": {
        "upstream": [],
        "downstream": []
      },
      "tw_stocks": [
        {
          "code": "3443",
          "name": "創意"
        }
      ],
      "us_stocks": [
        {
          "ticker": "AUR",
          "name": "Aurora Innovation, Inc."
        }
      ],
      "auto_created": true,
      "auto_created_at": "2026-05-05"
    },
    {
      "id": "hbm_concept",
      "name": "HBM",
      "keyword": "HBM",
      "supply_chain": {
        "upstream": [],
        "downstream": []
      },
      "tw_stocks": [
        {
          "code": "3443",
          "name": "創意"
        },
        {
          "code": "1303",
          "name": "南亞"
        },
        {
          "code": "6488",
          "name": "環球晶"
        },
        {
          "code": "6770",
          "name": "力積電"
        }
      ],
      "us_stocks": [
        {
          "ticker": "MU",
          "name": "Micron Technology, Inc."
        }
      ],
      "auto_created": true,
      "auto_created_at": "2026-05-05"
    },
    {
      "id": "gallium_arsenide_concept",
      "name": "砷化鎵",
      "keyword": "砷化鎵",
      "supply_chain": {
        "upstream": [],
        "downstream": []
      },
      "tw_stocks": [
        {
          "code": "3105",
          "name": "穩懋"
        },
        {
          "code": "2303",
          "name": "聯電"
        },
        {
          "code": "8086",
          "name": "宏捷科"
        }
      ],
      "us_stocks": [],
      "auto_created": true,
      "auto_created_at": "2026-05-05"
    },
    {
      "id": "power_amplifier_concept",
      "name": "功率放大器",
      "keyword": "功率放大器",
      "supply_chain": {
        "upstream": [],
        "downstream": []
      },
      "tw_stocks": [
        {
          "code": "3105",
          "name": "穩懋"
        },
        {
          "code": "2303",
          "name": "聯電"
        },
        {
          "code": "8086",
          "name": "宏捷科"
        }
      ],
      "us_stocks": [
        {
          "ticker": "QCOM",
          "name": "QUALCOMM Incorporated"
        }
      ],
      "auto_created": true,
      "auto_created_at": "2026-05-05"
    },
    {
      "id": "optical_communication_concept",
      "name": "光通訊",
      "keyword": "光通訊",
      "supply_chain": {
        "upstream": [],
        "downstream": []
      },
      "tw_stocks": [
        {
          "code": "3105",
          "name": "穩懋"
        },
        {
          "code": "4958",
          "name": "臻鼎-KY"
        },
        {
          "code": "6147",
          "name": "頎邦"
        },
        {
          "code": "2303",
          "name": "聯電"
        },
        {
          "code": "3481",
          "name": "群創"
        },
        {
          "code": "2455",
          "name": "全新"
        },
        {
          "code": "2345",
          "name": "智邦"
        },
        {
          "code": "2360",
          "name": "致茂"
        },
        {
          "code": "4979",
          "name": "華星光"
        },
        {
          "code": "3081",
          "name": "聯亞"
        },
        {
          "code": "6285",
          "name": "啟碁"
        },
        {
          "code": "8086",
          "name": "宏捷科"
        },
        {
          "code": "3264",
          "name": "欣銓"
        },
        {
          "code": "4991",
          "name": "環宇-KY"
        }
      ],
      "us_stocks": [
        {
          "ticker": "NOK",
          "name": "Nokia Corporation Sponsored"
        },
        {
          "ticker": "GLW",
          "name": "Corning Incorporated"
        },
        {
          "ticker": "HIMX",
          "name": "Himax Technologies, Inc."
        }
      ],
      "auto_created": true,
      "auto_created_at": "2026-05-05"
    },
    {
      "id": "ssd_controller_concept",
      "name": "SSD控制器",
      "keyword": "SSD控制器",
      "supply_chain": {
        "upstream": [],
        "downstream": []
      },
      "tw_stocks": [
        {
          "code": "8299",
          "name": "群聯"
        },
        {
          "code": "3260",
          "name": "威剛"
        }
      ],
      "us_stocks": [],
      "auto_created": true,
      "auto_created_at": "2026-05-05"
    },
    {
      "id": "embedded_odm_concept",
      "name": "嵌入式ODM",
      "keyword": "嵌入式ODM",
      "supply_chain": {
        "upstream": [],
        "downstream": []
      },
      "tw_stocks": [
        {
          "code": "8299",
          "name": "群聯"
        },
        {
          "code": "5289",
          "name": "宜鼎"
        },
        {
          "code": "3529",
          "name": "力旺"
        }
      ],
      "us_stocks": [],
      "auto_created": true,
      "auto_created_at": "2026-05-05"
    },
    {
      "id": "pcb_manufacturer",
      "name": "印刷電路板",
      "keyword": "印刷電路板",
      "supply_chain": {
        "upstream": [],
        "downstream": []
      },
      "tw_stocks": [
        {
          "code": "4958",
          "name": "臻鼎-KY"
        },
        {
          "code": "6274",
          "name": "台燿"
        },
        {
          "code": "2327",
          "name": "國巨*"
        },
        {
          "code": "8046",
          "name": "南電"
        },
        {
          "code": "1802",
          "name": "台玻"
        },
        {
          "code": "2383",
          "name": "台光電"
        },
        {
          "code": "1815",
          "name": "富喬"
        },
        {
          "code": "8358",
          "name": "金居"
        },
        {
          "code": "8210",
          "name": "勤誠"
        }
      ],
      "us_stocks": [],
      "auto_created": true,
      "auto_created_at": "2026-05-05"
    },
    {
      "id": "high_frequency_copper_foil_substrate",
      "name": "高頻銅箔基板",
      "keyword": "高頻銅箔基板",
      "supply_chain": {
        "upstream": [],
        "downstream": []
      },
      "tw_stocks": [
        {
          "code": "6274",
          "name": "台燿"
        },
        {
          "code": "2383",
          "name": "台光電"
        },
        {
          "code": "1815",
          "name": "富喬"
        },
        {
          "code": "8358",
          "name": "金居"
        }
      ],
      "us_stocks": [],
      "auto_created": true,
      "auto_created_at": "2026-05-05"
    },
    {
      "id": "rf_ic_packaging_concept",
      "name": "射頻元件",
      "keyword": "射頻元件",
      "supply_chain": {
        "upstream": [],
        "downstream": []
      },
      "tw_stocks": [
        {
          "code": "6147",
          "name": "頎邦"
        },
        {
          "code": "3264",
          "name": "欣銓"
        }
      ],
      "us_stocks": [
        {
          "ticker": "QCOM",
          "name": "QUALCOMM Incorporated"
        }
      ],
      "auto_created": true,
      "auto_created_at": "2026-05-05"
    },
    {
      "id": "foundry_concept",
      "name": "晶圓代工",
      "keyword": "晶圓代工",
      "supply_chain": {
        "upstream": [],
        "downstream": []
      },
      "tw_stocks": [
        {
          "code": "2303",
          "name": "聯電"
        },
        {
          "code": "6770",
          "name": "力積電"
        },
        {
          "code": "5347",
          "name": "世界"
        },
        {
          "code": "8086",
          "name": "宏捷科"
        },
        {
          "code": "4991",
          "name": "環宇-KY"
        }
      ],
      "us_stocks": [],
      "auto_created": true,
      "auto_created_at": "2026-05-05"
    },
    {
      "id": "passive_components_concept",
      "name": "被動元件",
      "keyword": "被動元件",
      "supply_chain": {
        "upstream": [],
        "downstream": []
      },
      "tw_stocks": [
        {
          "code": "2327",
          "name": "國巨*"
        },
        {
          "code": "6187",
          "name": "萬潤"
        }
      ],
      "us_stocks": [],
      "auto_created": true,
      "auto_created_at": "2026-05-05"
    },
    {
      "id": "tantalum_capacitor_concept",
      "name": "鉭電容",
      "keyword": "鉭電容",
      "supply_chain": {
        "upstream": [],
        "downstream": []
      },
      "tw_stocks": [
        {
          "code": "2327",
          "name": "國巨*"
        }
      ],
      "us_stocks": [],
      "auto_created": true,
      "auto_created_at": "2026-05-05"
    },
    {
      "id": "sensor_concept",
      "name": "感測器",
      "keyword": "感測器",
      "supply_chain": {
        "upstream": [],
        "downstream": []
      },
      "tw_stocks": [
        {
          "code": "2327",
          "name": "國巨*"
        },
        {
          "code": "3529",
          "name": "力旺"
        },
        {
          "code": "3406",
          "name": "玉晶光"
        }
      ],
      "us_stocks": [
        {
          "ticker": "HIMX",
          "name": "Himax Technologies, Inc."
        }
      ],
      "auto_created": true,
      "auto_created_at": "2026-05-05"
    },
    {
      "id": "agentic_ai_concept",
      "name": "Agentic AI",
      "keyword": "Agentic AI",
      "supply_chain": {
        "upstream": [],
        "downstream": []
      },
      "tw_stocks": [
        {
          "code": "3260",
          "name": "威剛"
        },
        {
          "code": "5289",
          "name": "宜鼎"
        }
      ],
      "us_stocks": [
        {
          "ticker": "PLTR",
          "name": "Palantir Technologies Inc."
        },
        {
          "ticker": "SOUN",
          "name": "SoundHound AI, Inc."
        },
        {
          "ticker": "BBAI",
          "name": "BigBear.ai, Inc."
        },
        {
          "ticker": "NU",
          "name": "Nu Holdings Ltd."
        }
      ],
      "auto_created": true,
      "auto_created_at": "2026-05-05"
    },
    {
      "id": "display_panel_concept",
      "name": "顯示面板",
      "keyword": "顯示面板",
      "supply_chain": {
        "upstream": [],
        "downstream": []
      },
      "tw_stocks": [
        {
          "code": "3481",
          "name": "群創"
        },
        {
          "code": "4749",
          "name": "新應材"
        },
        {
          "code": "8069",
          "name": "元太"
        }
      ],
      "us_stocks": [
        {
          "ticker": "GLW",
          "name": "Corning Incorporated"
        },
        {
          "ticker": "HIMX",
          "name": "Himax Technologies, Inc."
        }
      ],
      "auto_created": true,
      "auto_created_at": "2026-05-05"
    },
    {
      "id": "automotive_electronics_concept",
      "name": "車用電子",
      "keyword": "車用電子",
      "supply_chain": {
        "upstream": [],
        "downstream": []
      },
      "tw_stocks": [
        {
          "code": "3481",
          "name": "群創"
        },
        {
          "code": "6488",
          "name": "環球晶"
        },
        {
          "code": "3211",
          "name": "順達"
        },
        {
          "code": "3529",
          "name": "力旺"
        },
        {
          "code": "8086",
          "name": "宏捷科"
        },
        {
          "code": "3264",
          "name": "欣銓"
        },
        {
          "code": "3406",
          "name": "玉晶光"
        }
      ],
      "us_stocks": [
        {
          "ticker": "TSLA",
          "name": "Tesla, Inc."
        },
        {
          "ticker": "F",
          "name": "Ford Motor Company"
        },
        {
          "ticker": "NIO",
          "name": "NIO Inc."
        },
        {
          "ticker": "HIMX",
          "name": "Himax Technologies, Inc."
        },
        {
          "ticker": "BB",
          "name": "BlackBerry Limited"
        }
      ],
      "auto_created": true,
      "auto_created_at": "2026-05-05"
    },
    {
      "id": "glass_substrate_concept",
      "name": "玻璃基板",
      "keyword": "玻璃基板",
      "supply_chain": {
        "upstream": [],
        "downstream": []
      },
      "tw_stocks": [
        {
          "code": "8046",
          "name": "南電"
        },
        {
          "code": "1802",
          "name": "台玻"
        }
      ],
      "us_stocks": [
        {
          "ticker": "GLW",
          "name": "Corning Incorporated"
        }
      ],
      "auto_created": true,
      "auto_created_at": "2026-05-05"
    },
    {
      "id": "bt_substrate_concept",
      "name": "BT載板",
      "keyword": "BT載板",
      "supply_chain": {
        "upstream": [],
        "downstream": []
      },
      "tw_stocks": [
        {
          "code": "8046",
          "name": "南電"
        }
      ],
      "us_stocks": [],
      "auto_created": true,
      "auto_created_at": "2026-05-05"
    },
    {
      "id": "indium_phosphide_concept",
      "name": "磷化銦",
      "keyword": "磷化銦",
      "supply_chain": {
        "upstream": [],
        "downstream": []
      },
      "tw_stocks": [
        {
          "code": "2455",
          "name": "全新"
        },
        {
          "code": "8086",
          "name": "宏捷科"
        }
      ],
      "us_stocks": [],
      "auto_created": true,
      "auto_created_at": "2026-05-05"
    },
    {
      "id": "silicon_wafer_manufacturer",
      "name": "矽晶圓",
      "keyword": "矽晶圓",
      "supply_chain": {
        "upstream": [],
        "downstream": []
      },
      "tw_stocks": [
        {
          "code": "6488",
          "name": "環球晶"
        },
        {
          "code": "6182",
          "name": "合晶"
        }
      ],
      "us_stocks": [],
      "auto_created": true,
      "auto_created_at": "2026-05-05"
    },
    {
      "id": "compound_semiconductor_concept",
      "name": "化合物半導體",
      "keyword": "化合物半導體",
      "supply_chain": {
        "upstream": [],
        "downstream": []
      },
      "tw_stocks": [
        {
          "code": "6488",
          "name": "環球晶"
        },
        {
          "code": "8086",
          "name": "宏捷科"
        }
      ],
      "us_stocks": [],
      "auto_created": true,
      "auto_created_at": "2026-05-05"
    },
    {
      "id": "low_dk_glass_fiber_cloth_concept",
      "name": "低介電玻璃纖維布",
      "keyword": "Low DK 玻璃纖維布",
      "supply_chain": {
        "upstream": [],
        "downstream": []
      },
      "tw_stocks": [
        {
          "code": "1802",
          "name": "台玻"
        },
        {
          "code": "1815",
          "name": "富喬"
        }
      ],
      "us_stocks": [],
      "auto_created": true,
      "auto_created_at": "2026-05-05"
    },
    {
      "id": "low_e_glass_concept",
      "name": "節能玻璃",
      "keyword": "Low-E 玻璃",
      "supply_chain": {
        "upstream": [],
        "downstream": []
      },
      "tw_stocks": [
        {
          "code": "1802",
          "name": "台玻"
        }
      ],
      "us_stocks": [],
      "auto_created": true,
      "auto_created_at": "2026-05-05"
    },
    {
      "id": "energy_storage_solutions",
      "name": "儲能",
      "keyword": "儲能",
      "supply_chain": {
        "upstream": [],
        "downstream": []
      },
      "tw_stocks": [
        {
          "code": "2301",
          "name": "光寶科"
        },
        {
          "code": "2360",
          "name": "致茂"
        }
      ],
      "us_stocks": [
        {
          "ticker": "TSLA",
          "name": "Tesla, Inc."
        },
        {
          "ticker": "FLNC",
          "name": "Fluence Energy, Inc."
        },
        {
          "ticker": "AMPX",
          "name": "Amprius Technologies, Inc."
        },
        {
          "ticker": "EOSE",
          "name": "Eos Energy Enterprises, Inc."
        }
      ],
      "auto_created": true,
      "auto_created_at": "2026-05-05"
    },
    {
      "id": "energy_generation_solutions",
      "name": "發電",
      "keyword": "發電",
      "supply_chain": {
        "upstream": [],
        "downstream": []
      },
      "tw_stocks": [],
      "us_stocks": [
        {
          "ticker": "TSLA",
          "name": "Tesla, Inc."
        },
        {
          "ticker": "GLW",
          "name": "Corning Incorporated"
        }
      ],
      "auto_created": true,
      "auto_created_at": "2026-05-05"
    },
    {
      "id": "e_commerce_platform",
      "name": "電商平台",
      "keyword": "電商平台",
      "supply_chain": {
        "upstream": [],
        "downstream": []
      },
      "tw_stocks": [],
      "us_stocks": [
        {
          "ticker": "AMZN",
          "name": "Amazon.com, Inc."
        },
        {
          "ticker": "PYPL",
          "name": "PayPal Holdings, Inc."
        },
        {
          "ticker": "PINS",
          "name": "Pinterest, Inc."
        },
        {
          "ticker": "GRAB",
          "name": "Grab Holdings Limited"
        },
        {
          "ticker": "SHOP",
          "name": "Shopify Inc."
        },
        {
          "ticker": "UBER",
          "name": "Uber Technologies, Inc."
        },
        {
          "ticker": "CPNG",
          "name": "Coupang, Inc."
        },
        {
          "ticker": "COMP",
          "name": "Compass, Inc."
        },
        {
          "ticker": "U",
          "name": "Unity Software Inc."
        },
        {
          "ticker": "NU",
          "name": "Nu Holdings Ltd."
        },
        {
          "ticker": "OPEN",
          "name": "Opendoor Technologies Inc"
        }
      ],
      "auto_created": true,
      "auto_created_at": "2026-05-05"
    },
    {
      "id": "cloud_computing_service",
      "name": "雲端運算",
      "keyword": "雲端運算",
      "supply_chain": {
        "upstream": [],
        "downstream": []
      },
      "tw_stocks": [],
      "us_stocks": [
        {
          "ticker": "AMZN",
          "name": "Amazon.com, Inc."
        },
        {
          "ticker": "IREN",
          "name": "IREN LIMITED"
        },
        {
          "ticker": "SOFI",
          "name": "SoFi Technologies, Inc."
        },
        {
          "ticker": "SNAP",
          "name": "Snap Inc."
        },
        {
          "ticker": "UBER",
          "name": "Uber Technologies, Inc."
        },
        {
          "ticker": "BBAI",
          "name": "BigBear.ai, Inc."
        },
        {
          "ticker": "DDOG",
          "name": "Datadog, Inc."
        },
        {
          "ticker": "ORCL",
          "name": "Oracle Corporation"
        },
        {
          "ticker": "U",
          "name": "Unity Software Inc."
        },
        {
          "ticker": "CRWV",
          "name": "CoreWeave, Inc."
        },
        {
          "ticker": "NU",
          "name": "Nu Holdings Ltd."
        }
      ],
      "auto_created": true,
      "auto_created_at": "2026-05-05"
    },
    {
      "id": "digital_advertising",
      "name": "數位廣告",
      "keyword": "數位廣告",
      "supply_chain": {
        "upstream": [],
        "downstream": []
      },
      "tw_stocks": [],
      "us_stocks": [
        {
          "ticker": "AMZN",
          "name": "Amazon.com, Inc."
        },
        {
          "ticker": "PINS",
          "name": "Pinterest, Inc."
        },
        {
          "ticker": "GRAB",
          "name": "Grab Holdings Limited"
        },
        {
          "ticker": "SNAP",
          "name": "Snap Inc."
        },
        {
          "ticker": "UBER",
          "name": "Uber Technologies, Inc."
        },
        {
          "ticker": "U",
          "name": "Unity Software Inc."
        },
        {
          "ticker": "TTD",
          "name": "The Trade Desk, Inc."
        }
      ],
      "auto_created": true,
      "auto_created_at": "2026-05-05"
    },
    {
      "id": "cell_therapy_biotech",
      "name": "細胞治療",
      "keyword": "細胞治療",
      "supply_chain": {
        "upstream": [],
        "downstream": []
      },
      "tw_stocks": [],
      "us_stocks": [
        {
          "ticker": "ACLX",
          "name": "Arcellx, Inc."
        },
        {
          "ticker": "TERN",
          "name": "Terns Pharmaceuticals, Inc."
        }
      ],
      "auto_created": true,
      "auto_created_at": "2026-05-05"
    },
    {
      "id": "immunotherapy_biotech",
      "name": "免疫療法",
      "keyword": "免疫療法",
      "supply_chain": {
        "upstream": [],
        "downstream": []
      },
      "tw_stocks": [],
      "us_stocks": [
        {
          "ticker": "ACLX",
          "name": "Arcellx, Inc."
        },
        {
          "ticker": "TERN",
          "name": "Terns Pharmaceuticals, Inc."
        }
      ],
      "auto_created": true,
      "auto_created_at": "2026-05-05"
    },
    {
      "id": "stablecoin_concept",
      "name": "穩定幣",
      "keyword": "穩定幣",
      "supply_chain": {
        "upstream": [],
        "downstream": []
      },
      "tw_stocks": [],
      "us_stocks": [
        {
          "ticker": "CRCL",
          "name": "Circle Internet Group, Inc."
        }
      ],
      "auto_created": true,
      "auto_created_at": "2026-05-05"
    },
    {
      "id": "cryptocurrency_infrastructure",
      "name": "加密貨幣基礎設施",
      "keyword": "加密貨幣基礎設施",
      "supply_chain": {
        "upstream": [],
        "downstream": []
      },
      "tw_stocks": [],
      "us_stocks": [
        {
          "ticker": "CRCL",
          "name": "Circle Internet Group, Inc."
        },
        {
          "ticker": "IREN",
          "name": "IREN LIMITED"
        },
        {
          "ticker": "WULF",
          "name": "TeraWulf Inc."
        },
        {
          "ticker": "CORZ",
          "name": "Core Scientific, Inc."
        }
      ],
      "auto_created": true,
      "auto_created_at": "2026-05-05"
    },
    {
      "id": "fintech_lending_platform",
      "name": "金融科技",
      "keyword": "金融科技",
      "supply_chain": {
        "upstream": [],
        "downstream": []
      },
      "tw_stocks": [],
      "us_stocks": [
        {
          "ticker": "SOFI",
          "name": "SoFi Technologies, Inc."
        },
        {
          "ticker": "GRAB",
          "name": "Grab Holdings Limited"
        },
        {
          "ticker": "ITUB",
          "name": "Itau Unibanco Banco Holding SA"
        },
        {
          "ticker": "BBD",
          "name": "Banco Bradesco Sa"
        },
        {
          "ticker": "NU",
          "name": "Nu Holdings Ltd."
        }
      ],
      "auto_created": true,
      "auto_created_at": "2026-05-05"
    },
    {
      "id": "immersion_cooling_concept",
      "name": "浸沒冷卻",
      "keyword": "浸沒冷卻",
      "supply_chain": {
        "upstream": [],
        "downstream": []
      },
      "tw_stocks": [],
      "us_stocks": [
        {
          "ticker": "BMNR",
          "name": "BitMine Immersion Technologies,"
        }
      ],
      "auto_created": true,
      "auto_created_at": "2026-05-05"
    },
    {
      "id": "data_center_equipment_concept",
      "name": "資料中心設備",
      "keyword": "資料中心設備",
      "supply_chain": {
        "upstream": [],
        "downstream": []
      },
      "tw_stocks": [
        {
          "code": "3665",
          "name": "貿聯-KY"
        },
        {
          "code": "2301",
          "name": "光寶科"
        },
        {
          "code": "3189",
          "name": "景碩"
        },
        {
          "code": "2345",
          "name": "智邦"
        },
        {
          "code": "4979",
          "name": "華星光"
        },
        {
          "code": "8210",
          "name": "勤誠"
        },
        {
          "code": "5274",
          "name": "信驊"
        },
        {
          "code": "3324",
          "name": "雙鴻"
        }
      ],
      "us_stocks": [
        {
          "ticker": "BMNR",
          "name": "BitMine Immersion Technologies,"
        },
        {
          "ticker": "GLW",
          "name": "Corning Incorporated"
        },
        {
          "ticker": "SMCI",
          "name": "Super Micro Computer, Inc."
        },
        {
          "ticker": "WULF",
          "name": "TeraWulf Inc."
        },
        {
          "ticker": "BBAI",
          "name": "BigBear.ai, Inc."
        },
        {
          "ticker": "DDOG",
          "name": "Datadog, Inc."
        },
        {
          "ticker": "CRWV",
          "name": "CoreWeave, Inc."
        }
      ],
      "auto_created": true,
      "auto_created_at": "2026-05-05"
    },
    {
      "id": "cruise_line_operator",
      "name": "郵輪",
      "keyword": "郵輪",
      "supply_chain": {
        "upstream": [],
        "downstream": []
      },
      "tw_stocks": [],
      "us_stocks": [
        {
          "ticker": "CCL",
          "name": "Carnival Corporation"
        },
        {
          "ticker": "AAL",
          "name": "American Airlines Group, Inc."
        },
        {
          "ticker": "CUK",
          "name": "Carnival Plc"
        }
      ],
      "auto_created": true,
      "auto_created_at": "2026-05-05"
    },
    {
      "id": "direct_lending_bdc_concept",
      "name": "直接借貸",
      "keyword": "直接借貸",
      "supply_chain": {
        "upstream": [],
        "downstream": []
      },
      "tw_stocks": [],
      "us_stocks": [
        {
          "ticker": "OWL",
          "name": "Blue Owl Capital Inc."
        },
        {
          "ticker": "BBD",
          "name": "Banco Bradesco Sa"
        }
      ],
      "auto_created": true,
      "auto_created_at": "2026-05-05"
    },
    {
      "id": "private_credit_concept",
      "name": "私募信貸",
      "keyword": "私募信貸",
      "supply_chain": {
        "upstream": [],
        "downstream": []
      },
      "tw_stocks": [],
      "us_stocks": [
        {
          "ticker": "OWL",
          "name": "Blue Owl Capital Inc."
        },
        {
          "ticker": "BBD",
          "name": "Banco Bradesco Sa"
        }
      ],
      "auto_created": true,
      "auto_created_at": "2026-05-05"
    },
    {
      "id": "financial_services_investment",
      "name": "金融服務",
      "keyword": "金融服務",
      "supply_chain": {
        "upstream": [],
        "downstream": []
      },
      "tw_stocks": [],
      "us_stocks": [
        {
          "ticker": "OWL",
          "name": "Blue Owl Capital Inc."
        },
        {
          "ticker": "ABEV",
          "name": "Ambev S.A."
        },
        {
          "ticker": "CRBG",
          "name": "Corebridge Financial Inc."
        },
        {
          "ticker": "ITUB",
          "name": "Itau Unibanco Banco Holding SA"
        },
        {
          "ticker": "BBD",
          "name": "Banco Bradesco Sa"
        },
        {
          "ticker": "NU",
          "name": "Nu Holdings Ltd."
        },
        {
          "ticker": "OPEN",
          "name": "Opendoor Technologies Inc"
        }
      ],
      "auto_created": true,
      "auto_created_at": "2026-05-05"
    },
    {
      "id": "offshore_drilling_contractor_concept",
      "name": "離岸鑽探",
      "keyword": "離岸鑽探",
      "supply_chain": {
        "upstream": [],
        "downstream": []
      },
      "tw_stocks": [],
      "us_stocks": [
        {
          "ticker": "RIG",
          "name": "Transocean Ltd (Switzerland)"
        },
        {
          "ticker": "CTRA",
          "name": "Coterra Energy Inc."
        }
      ],
      "auto_created": true,
      "auto_created_at": "2026-05-05"
    },
    {
      "id": "conversational_ai_concept",
      "name": "對話式AI",
      "keyword": "對話式AI",
      "supply_chain": {
        "upstream": [],
        "downstream": []
      },
      "tw_stocks": [],
      "us_stocks": [
        {
          "ticker": "SOUN",
          "name": "SoundHound AI, Inc."
        },
        {
          "ticker": "NU",
          "name": "Nu Holdings Ltd."
        }
      ],
      "auto_created": true,
      "auto_created_at": "2026-05-05"
    },
    {
      "id": "hydrogen_energy_concept",
      "name": "氫能",
      "keyword": "氫能",
      "supply_chain": {
        "upstream": [],
        "downstream": []
      },
      "tw_stocks": [],
      "us_stocks": [
        {
          "ticker": "PLUG",
          "name": "Plug Power, Inc."
        }
      ],
      "auto_created": true,
      "auto_created_at": "2026-05-05"
    },
    {
      "id": "advanced_air_mobility_concept",
      "name": "空中計程車",
      "keyword": "空中計程車",
      "supply_chain": {
        "upstream": [],
        "downstream": []
      },
      "tw_stocks": [],
      "us_stocks": [
        {
          "ticker": "ACHR",
          "name": "Archer Aviation Inc."
        },
        {
          "ticker": "JOBY",
          "name": "Joby Aviation, Inc."
        }
      ],
      "auto_created": true,
      "auto_created_at": "2026-05-06"
    },
    {
      "id": "social_media_platform",
      "name": "社群媒體",
      "keyword": "社群媒體",
      "supply_chain": {
        "upstream": [],
        "downstream": []
      },
      "tw_stocks": [],
      "us_stocks": [
        {
          "ticker": "SNAP",
          "name": "Snap Inc."
        }
      ],
      "auto_created": true,
      "auto_created_at": "2026-05-06"
    },
    {
      "id": "high_end_materials_concept",
      "name": "高階材料",
      "keyword": "高階材料",
      "supply_chain": {
        "upstream": [],
        "downstream": []
      },
      "tw_stocks": [
        {
          "code": "2383",
          "name": "台光電"
        },
        {
          "code": "1785",
          "name": "光洋科"
        }
      ],
      "us_stocks": [],
      "auto_created": true,
      "auto_created_at": "2026-05-06"
    },
    {
      "id": "power_management_system_concept",
      "name": "電源管理",
      "keyword": "電源管理",
      "supply_chain": {
        "upstream": [],
        "downstream": []
      },
      "tw_stocks": [
        {
          "code": "2301",
          "name": "光寶科"
        },
        {
          "code": "6770",
          "name": "力積電"
        },
        {
          "code": "3211",
          "name": "順達"
        },
        {
          "code": "3529",
          "name": "力旺"
        }
      ],
      "us_stocks": [],
      "auto_created": true,
      "auto_created_at": "2026-05-06"
    },
    {
      "id": "cpo_testing_concept",
      "name": "CPO測試",
      "keyword": "CPO測試",
      "supply_chain": {
        "upstream": [],
        "downstream": []
      },
      "tw_stocks": [
        {
          "code": "2360",
          "name": "致茂"
        },
        {
          "code": "6223",
          "name": "旺矽"
        }
      ],
      "us_stocks": [],
      "auto_created": true,
      "auto_created_at": "2026-05-06"
    },
    {
      "id": "measurement_and_testing_equipment",
      "name": "量測設備",
      "keyword": "量測設備",
      "supply_chain": {
        "upstream": [],
        "downstream": []
      },
      "tw_stocks": [
        {
          "code": "2360",
          "name": "致茂"
        },
        {
          "code": "3008",
          "name": "大立光"
        }
      ],
      "us_stocks": [],
      "auto_created": true,
      "auto_created_at": "2026-05-06"
    },
    {
      "id": "semiconductor_materials_concept",
      "name": "半導體材料",
      "keyword": "半導體材料",
      "supply_chain": {
        "upstream": [],
        "downstream": []
      },
      "tw_stocks": [
        {
          "code": "1815",
          "name": "富喬"
        },
        {
          "code": "1785",
          "name": "光洋科"
        },
        {
          "code": "8358",
          "name": "金居"
        },
        {
          "code": "6223",
          "name": "旺矽"
        },
        {
          "code": "4749",
          "name": "新應材"
        }
      ],
      "us_stocks": [
        {
          "ticker": "GLW",
          "name": "Corning Incorporated"
        }
      ],
      "auto_created": true,
      "auto_created_at": "2026-05-06"
    },
    {
      "id": "solar_wafer_concept",
      "name": "太陽能矽晶圓",
      "keyword": "太陽能矽晶圓",
      "supply_chain": {
        "upstream": [],
        "downstream": []
      },
      "tw_stocks": [],
      "us_stocks": [
        {
          "ticker": "GLW",
          "name": "Corning Incorporated"
        }
      ],
      "auto_created": true,
      "auto_created_at": "2026-05-06"
    },
    {
      "id": "quantum_computing_concept",
      "name": "量子運算",
      "keyword": "量子運算",
      "supply_chain": {
        "upstream": [],
        "downstream": []
      },
      "tw_stocks": [],
      "us_stocks": [
        {
          "ticker": "IONQ",
          "name": "IonQ, Inc."
        }
      ],
      "auto_created": true,
      "auto_created_at": "2026-05-06"
    },
    {
      "id": "digital_asset_mining",
      "name": "數位資產挖礦",
      "keyword": "數位資產挖礦",
      "supply_chain": {
        "upstream": [],
        "downstream": []
      },
      "tw_stocks": [],
      "us_stocks": [
        {
          "ticker": "CORZ",
          "name": "Core Scientific, Inc."
        }
      ],
      "auto_created": true,
      "auto_created_at": "2026-05-06"
    },
    {
      "id": "autonomous_driving_concept",
      "name": "自動駕駛",
      "keyword": "自動駕駛",
      "supply_chain": {
        "upstream": [],
        "downstream": []
      },
      "tw_stocks": [],
      "us_stocks": [
        {
          "ticker": "AUR",
          "name": "Aurora Innovation, Inc."
        }
      ],
      "auto_created": true,
      "auto_created_at": "2026-05-06"
    },
    {
      "id": "autonomous_trucking_concept",
      "name": "自動駕駛卡車",
      "keyword": "自動駕駛卡車",
      "supply_chain": {
        "upstream": [],
        "downstream": []
      },
      "tw_stocks": [],
      "us_stocks": [
        {
          "ticker": "AUR",
          "name": "Aurora Innovation, Inc."
        }
      ],
      "auto_created": true,
      "auto_created_at": "2026-05-06"
    },
    {
      "id": "small_modular_reactor_concept",
      "name": "小型模組化反應爐",
      "keyword": "小型模組化反應爐",
      "supply_chain": {
        "upstream": [],
        "downstream": []
      },
      "tw_stocks": [],
      "us_stocks": [
        {
          "ticker": "SMR",
          "name": "NuScale Power Corporation"
        }
      ],
      "auto_created": true,
      "auto_created_at": "2026-05-07"
    },
    {
      "id": "predictive_analytics_software",
      "name": "預測分析",
      "keyword": "預測分析軟體",
      "supply_chain": {
        "upstream": [],
        "downstream": []
      },
      "tw_stocks": [],
      "us_stocks": [
        {
          "ticker": "BBAI",
          "name": "BigBear.ai, Inc."
        }
      ],
      "auto_created": true,
      "auto_created_at": "2026-05-07"
    },
    {
      "id": "cyber_engineering",
      "name": "網路工程",
      "keyword": "網路工程",
      "supply_chain": {
        "upstream": [],
        "downstream": []
      },
      "tw_stocks": [],
      "us_stocks": [
        {
          "ticker": "BBAI",
          "name": "BigBear.ai, Inc."
        },
        {
          "ticker": "BB",
          "name": "BlackBerry Limited"
        }
      ],
      "auto_created": true,
      "auto_created_at": "2026-05-07"
    },
    {
      "id": "cpo_concept",
      "name": "CPO",
      "keyword": "CPO",
      "supply_chain": {
        "upstream": [],
        "downstream": []
      },
      "tw_stocks": [
        {
          "code": "4979",
          "name": "華星光"
        }
      ],
      "us_stocks": [
        {
          "ticker": "HIMX",
          "name": "Himax Technologies, Inc."
        }
      ],
      "auto_created": true,
      "auto_created_at": "2026-05-07"
    },
    {
      "id": "lpddr_memory_concept",
      "name": "低功耗記憶體",
      "keyword": "LPDDR",
      "supply_chain": {
        "upstream": [],
        "downstream": []
      },
      "tw_stocks": [
        {
          "code": "5289",
          "name": "宜鼎"
        }
      ],
      "us_stocks": [],
      "auto_created": true,
      "auto_created_at": "2026-05-07"
    },
    {
      "id": "cxl_memory_concept",
      "name": "CXL記憶體",
      "keyword": "CXL",
      "supply_chain": {
        "upstream": [],
        "downstream": []
      },
      "tw_stocks": [
        {
          "code": "5289",
          "name": "宜鼎"
        }
      ],
      "us_stocks": [],
      "auto_created": true,
      "auto_created_at": "2026-05-07"
    },
    {
      "id": "circular_economy_concept",
      "name": "循環經濟",
      "keyword": "循環經濟",
      "supply_chain": {
        "upstream": [],
        "downstream": []
      },
      "tw_stocks": [
        {
          "code": "1785",
          "name": "光洋科"
        }
      ],
      "us_stocks": [],
      "auto_created": true,
      "auto_created_at": "2026-05-07"
    },
    {
      "id": "precious_metals_trading",
      "name": "貴金屬",
      "keyword": "貴金屬",
      "supply_chain": {
        "upstream": [],
        "downstream": []
      },
      "tw_stocks": [
        {
          "code": "1785",
          "name": "光洋科"
        }
      ],
      "us_stocks": [
        {
          "ticker": "BTG",
          "name": "B2Gold Corp"
        }
      ],
      "auto_created": true,
      "auto_created_at": "2026-05-07"
    },
    {
      "id": "connected_fitness_equipment",
      "name": "智慧健身",
      "keyword": "智慧健身",
      "supply_chain": {
        "upstream": [],
        "downstream": []
      },
      "tw_stocks": [],
      "us_stocks": [
        {
          "ticker": "PTON",
          "name": "Peloton Interactive, Inc."
        }
      ],
      "auto_created": true,
      "auto_created_at": "2026-05-07"
    },
    {
      "id": "fitness_subscription_service",
      "name": "健身訂閱",
      "keyword": "健身訂閱",
      "supply_chain": {
        "upstream": [],
        "downstream": []
      },
      "tw_stocks": [],
      "us_stocks": [
        {
          "ticker": "PTON",
          "name": "Peloton Interactive, Inc."
        }
      ],
      "auto_created": true,
      "auto_created_at": "2026-05-07"
    },
    {
      "id": "enterprise_software_maker",
      "name": "企業軟體",
      "keyword": "企業軟體",
      "supply_chain": {
        "upstream": [],
        "downstream": []
      },
      "tw_stocks": [],
      "us_stocks": [
        {
          "ticker": "DDOG",
          "name": "Datadog, Inc."
        }
      ],
      "auto_created": true,
      "auto_created_at": "2026-05-07"
    },
    {
      "id": "oracle_cloud_infrastructure",
      "name": "Oracle雲",
      "keyword": "Oracle雲",
      "supply_chain": {
        "upstream": [],
        "downstream": []
      },
      "tw_stocks": [],
      "us_stocks": [
        {
          "ticker": "ORCL",
          "name": "Oracle Corporation"
        }
      ],
      "auto_created": true,
      "auto_created_at": "2026-05-07"
    },
    {
      "id": "wiseeye_ai_sensing",
      "name": "AI感測",
      "keyword": "AI感測",
      "supply_chain": {
        "upstream": [],
        "downstream": []
      },
      "tw_stocks": [],
      "us_stocks": [
        {
          "ticker": "HIMX",
          "name": "Himax Technologies, Inc."
        }
      ],
      "auto_created": true,
      "auto_created_at": "2026-05-07"
    },
    {
      "id": "endpoint_ai",
      "name": "邊緣AI",
      "keyword": "邊緣AI",
      "supply_chain": {
        "upstream": [],
        "downstream": []
      },
      "tw_stocks": [],
      "us_stocks": [
        {
          "ticker": "HIMX",
          "name": "Himax Technologies, Inc."
        },
        {
          "ticker": "QCOM",
          "name": "QUALCOMM Incorporated"
        }
      ],
      "auto_created": true,
      "auto_created_at": "2026-05-07"
    },
    {
      "id": "silicon_anode_battery_concept",
      "name": "矽負極電池",
      "keyword": "矽負極電池",
      "supply_chain": {
        "upstream": [],
        "downstream": []
      },
      "tw_stocks": [],
      "us_stocks": [
        {
          "ticker": "AMPX",
          "name": "Amprius Technologies, Inc."
        }
      ],
      "auto_created": true,
      "auto_created_at": "2026-05-07"
    },
    {
      "id": "intelligent_edge_concept",
      "name": "智慧邊緣",
      "keyword": "智慧邊緣",
      "supply_chain": {
        "upstream": [],
        "downstream": []
      },
      "tw_stocks": [],
      "us_stocks": [
        {
          "ticker": "QCOM",
          "name": "QUALCOMM Incorporated"
        }
      ],
      "auto_created": true,
      "auto_created_at": "2026-05-07"
    },
    {
      "id": "lead_frame_concept",
      "name": "導線架",
      "keyword": "導線架",
      "supply_chain": {
        "upstream": [],
        "downstream": []
      },
      "tw_stocks": [
        {
          "code": "3653",
          "name": "健策"
        }
      ],
      "us_stocks": [],
      "auto_created": true,
      "auto_created_at": "2026-05-08"
    },
    {
      "id": "electronic_components_concept",
      "name": "電子零件",
      "keyword": "電子零件",
      "supply_chain": {
        "upstream": [],
        "downstream": []
      },
      "tw_stocks": [
        {
          "code": "3653",
          "name": "健策"
        }
      ],
      "us_stocks": [],
      "auto_created": true,
      "auto_created_at": "2026-05-08"
    },
    {
      "id": "probe_card_concept",
      "name": "探針卡",
      "keyword": "探針卡",
      "supply_chain": {
        "upstream": [],
        "downstream": []
      },
      "tw_stocks": [
        {
          "code": "6223",
          "name": "旺矽"
        }
      ],
      "us_stocks": [],
      "auto_created": true,
      "auto_created_at": "2026-05-09"
    },
    {
      "id": "bmc_chip_concept",
      "name": "BMC晶片",
      "keyword": "BMC晶片",
      "supply_chain": {
        "upstream": [],
        "downstream": []
      },
      "tw_stocks": [
        {
          "code": "5274",
          "name": "信驊"
        }
      ],
      "us_stocks": [],
      "auto_created": true,
      "auto_created_at": "2026-05-09"
    },
    {
      "id": "lithography_materials_concept",
      "name": "微影材料",
      "keyword": "微影製程特化材料",
      "supply_chain": {
        "upstream": [],
        "downstream": []
      },
      "tw_stocks": [
        {
          "code": "4749",
          "name": "新應材"
        }
      ],
      "us_stocks": [],
      "auto_created": true,
      "auto_created_at": "2026-05-09"
    },
    {
      "id": "bbu_battery_concept",
      "name": "BBU電池",
      "keyword": "BBU電池",
      "supply_chain": {
        "upstream": [],
        "downstream": []
      },
      "tw_stocks": [
        {
          "code": "3211",
          "name": "順達"
        }
      ],
      "us_stocks": [],
      "auto_created": true,
      "auto_created_at": "2026-05-09"
    },
    {
      "id": "embedded_nvm_ip_concept",
      "name": "嵌入式NVM",
      "keyword": "嵌入式NVM",
      "supply_chain": {
        "upstream": [],
        "downstream": []
      },
      "tw_stocks": [
        {
          "code": "3529",
          "name": "力旺"
        }
      ],
      "us_stocks": [],
      "auto_created": true,
      "auto_created_at": "2026-05-09"
    },
    {
      "id": "high_speed_optical_module_components",
      "name": "高速光模組",
      "keyword": "高速光模組",
      "supply_chain": {
        "upstream": [],
        "downstream": []
      },
      "tw_stocks": [
        {
          "code": "8086",
          "name": "宏捷科"
        },
        {
          "code": "4991",
          "name": "環宇-KY"
        }
      ],
      "us_stocks": [],
      "auto_created": true,
      "auto_created_at": "2026-05-09"
    },
    {
      "id": "cw_laser_concept",
      "name": "CW雷射",
      "keyword": "CW雷射",
      "supply_chain": {
        "upstream": [],
        "downstream": []
      },
      "tw_stocks": [
        {
          "code": "4991",
          "name": "環宇-KY"
        }
      ],
      "us_stocks": [],
      "auto_created": true,
      "auto_created_at": "2026-05-09"
    },
    {
      "id": "pd_component_concept",
      "name": "PD元件",
      "keyword": "PD元件",
      "supply_chain": {
        "upstream": [],
        "downstream": []
      },
      "tw_stocks": [
        {
          "code": "4991",
          "name": "環宇-KY"
        }
      ],
      "us_stocks": [],
      "auto_created": true,
      "auto_created_at": "2026-05-09"
    },
    {
      "id": "high_speed_interface_chip",
      "name": "高速介面",
      "keyword": "高速介面晶片",
      "supply_chain": {
        "upstream": [],
        "downstream": []
      },
      "tw_stocks": [
        {
          "code": "4966",
          "name": "譜瑞-KY"
        }
      ],
      "us_stocks": [],
      "auto_created": true,
      "auto_created_at": "2026-05-09"
    },
    {
      "id": "ai_pc_concept",
      "name": "AI PC",
      "keyword": "AI PC",
      "supply_chain": {
        "upstream": [],
        "downstream": []
      },
      "tw_stocks": [
        {
          "code": "4966",
          "name": "譜瑞-KY"
        }
      ],
      "us_stocks": [],
      "auto_created": true,
      "auto_created_at": "2026-05-09"
    },
    {
      "id": "camera_module_concept",
      "name": "鏡頭模組",
      "keyword": "鏡頭模組",
      "supply_chain": {
        "upstream": [],
        "downstream": []
      },
      "tw_stocks": [
        {
          "code": "3406",
          "name": "玉晶光"
        }
      ],
      "us_stocks": [],
      "auto_created": true,
      "auto_created_at": "2026-05-09"
    },
    {
      "id": "space_launch_services",
      "name": "太空發射",
      "keyword": "太空發射",
      "supply_chain": {
        "upstream": [],
        "downstream": []
      },
      "tw_stocks": [],
      "us_stocks": [
        {
          "ticker": "RKLB",
          "name": "Rocket Lab Corporation"
        }
      ],
      "auto_created": true,
      "auto_created_at": "2026-05-09"
    },
    {
      "id": "rocket_manufacturing",
      "name": "火箭製造",
      "keyword": "火箭製造",
      "supply_chain": {
        "upstream": [],
        "downstream": []
      },
      "tw_stocks": [],
      "us_stocks": [
        {
          "ticker": "RKLB",
          "name": "Rocket Lab Corporation"
        }
      ],
      "auto_created": true,
      "auto_created_at": "2026-05-09"
    },
    {
      "id": "ai_cloud_services",
      "name": "AI雲服務",
      "keyword": "AI雲服務",
      "supply_chain": {
        "upstream": [],
        "downstream": []
      },
      "tw_stocks": [],
      "us_stocks": [
        {
          "ticker": "CRWV",
          "name": "CoreWeave, Inc."
        }
      ],
      "auto_created": true,
      "auto_created_at": "2026-05-09"
    },
    {
      "id": "space_infrastructure_supplier",
      "name": "太空基礎設施",
      "keyword": "太空基礎設施",
      "supply_chain": {
        "upstream": [],
        "downstream": []
      },
      "tw_stocks": [],
      "us_stocks": [
        {
          "ticker": "RDW",
          "name": "Redwire Corporation"
        }
      ],
      "auto_created": true,
      "auto_created_at": "2026-05-09"
    },
    {
      "id": "solar_array_manufacturer",
      "name": "太陽能陣列",
      "keyword": "太陽能陣列",
      "supply_chain": {
        "upstream": [],
        "downstream": []
      },
      "tw_stocks": [],
      "us_stocks": [
        {
          "ticker": "RDW",
          "name": "Redwire Corporation"
        }
      ],
      "auto_created": true,
      "auto_created_at": "2026-05-09"
    },
    {
      "id": "mortgage_lending_platform",
      "name": "房貸平台",
      "keyword": "房貸",
      "supply_chain": {
        "upstream": [],
        "downstream": []
      },
      "tw_stocks": [],
      "us_stocks": [
        {
          "ticker": "RKT",
          "name": "Rocket Companies, Inc."
        }
      ],
      "auto_created": true,
      "auto_created_at": "2026-05-09"
    },
    {
      "id": "financial_reporting_software",
      "name": "財報軟體",
      "keyword": "財報",
      "supply_chain": {
        "upstream": [],
        "downstream": []
      },
      "tw_stocks": [],
      "us_stocks": [
        {
          "ticker": "RKT",
          "name": "Rocket Companies, Inc."
        }
      ],
      "auto_created": true,
      "auto_created_at": "2026-05-09"
    },
    {
      "id": "digital_banking_platform",
      "name": "數位銀行",
      "keyword": "數位銀行",
      "supply_chain": {
        "upstream": [],
        "downstream": []
      },
      "tw_stocks": [],
      "us_stocks": [
        {
          "ticker": "NU",
          "name": "Nu Holdings Ltd."
        }
      ],
      "auto_created": true,
      "auto_created_at": "2026-05-09"
    },
    {
      "id": "secure_communication_concept",
      "name": "安全通訊",
      "keyword": "安全通訊",
      "supply_chain": {
        "upstream": [],
        "downstream": []
      },
      "tw_stocks": [],
      "us_stocks": [
        {
          "ticker": "BB",
          "name": "BlackBerry Limited"
        }
      ],
      "auto_created": true,
      "auto_created_at": "2026-05-09"
    }
  ]
}